data_quest_client/__init__.py
data_quest_client/dataquest_client.py
data_quest_client-0.1.3.dist-info/LICENSE
data_quest_client-0.1.3.dist-info/METADATA
data_quest_client-0.1.3.dist-info/WHEEL
data_quest_client-0.1.3.dist-info/top_level.txt
data_quest_client-0.1.3.dist-info/RECORD
