Metadata-Version: 2.1
Name: data-quest-client
Version: 0.1.3
Summary: This is a client package that is used to send queries to Dataquest API.
Author-email: Tyler Wilson <twilson@elliottmgmt.com>
Project-URL: Homepage, https://stash.elliottmgmt.com/projects/DAT/repos/dataquest-api-python-client/browse
Classifier: Programming Language :: Python :: 3
Classifier: License :: OSI Approved :: MIT License
Classifier: Operating System :: OS Independent
Requires-Python: >=3.7
License-File: LICENSE
Requires-Dist: requests (>=2.28.2)
Requires-Dist: msal (>=1.21.0)
